pyISBO_2024/__init__.py
pyISBO_2024/main.py
pyISBO_2024/SBO_grb/AutoRegression.py
pyISBO_2024/SBO_grb/DecisionTree.py
pyISBO_2024/SBO_grb/ExtraTrees.py
pyISBO_2024/SBO_grb/LinearRegression.py
pyISBO_2024/SBO_grb/LogisticRegression.py
pyISBO_2024/SBO_grb/NeuralNetwork.py
pyISBO_2024/SBO_grb/QuadraticRegression.py
pyISBO_2024/SBO_grb/RandomForest.py
pyISBO_2024/SBO_grb/__init__.py
pyISBO_2024/SBO_pulp/AutoRegression.py
pyISBO_2024/SBO_pulp/DecisionTree.py
pyISBO_2024/SBO_pulp/ExtraTrees.py
pyISBO_2024/SBO_pulp/LinearRegression.py
pyISBO_2024/SBO_pulp/LogisticRegression.py
pyISBO_2024/SBO_pulp/NeuralNetwork.py
pyISBO_2024/SBO_pulp/RandomForest.py
pyISBO_2024/SBO_pulp/__init__.py
pyISBO-1.1.0.dist-info/METADATA
pyISBO-1.1.0.dist-info/WHEEL
pyISBO-1.1.0.dist-info/license.txt
pyISBO-1.1.0.dist-info/top_level.txt
pyISBO-1.1.0.dist-info/RECORD
