Metadata-Version: 2.1
Name: pyISBO
Version: 1.1.0
Summary: An integrated Surrogate-Base Optimization Toolbox
Home-page: https://github.com/Shawn1eo/pyISBO
Author: Liu Xiangting and Zhu Zesheng
Author-email: liu-xt22@mails.tsinghua.edu.cn
License: UNKNOWN
Platform: UNKNOWN
